IdentifyOutliers/CustomIQRScaler.py
IdentifyOutliers/CustomMinMaxScaler.py
IdentifyOutliers/CustomRobustScaler.py
IdentifyOutliers/CustomZscoreScaler.py
IdentifyOutliers-0.1.0.dist-info/LICENSE.TXT
IdentifyOutliers-0.1.0.dist-info/METADATA
IdentifyOutliers-0.1.0.dist-info/WHEEL
IdentifyOutliers-0.1.0.dist-info/top_level.txt
IdentifyOutliers-0.1.0.dist-info/RECORD
