Metadata-Version: 2.1
Name: IdentifyOutliers
Version: 0.1.0
Summary: A Python package for efficient scaling and outlier handling of pandas DataFrames using the some of the most popular outlier elimination approaches.
Home-page: https://github.com/amithpdn/IdentifyOutliers/
Author: Amith Lokugamage
Author-email: amithpdn@gmail.com
Keywords: Data Science,Outliers,Data Preprocessing
Requires-Python: >=3.6
License-File: LICENSE.TXT
Requires-Dist: pandas
Requires-Dist: scikit-learn
Requires-Dist: numpy
